{"specification": [{"columns": ["Description", "ANN"], "rows": [[{"columns": ["LHFLX", {"files": [], "path": "../lat_lon/WHOI OAFlux/OAFlux-LHFLX-ANN-global.png", "meta": {}, "title": "ANN"}], "title": "LHFLX global"}, {"columns": ["SHFLX", {"files": [], "path": "../lat_lon/WHOI OAFlux/OAFlux-SHFLX-ANN-global.png", "meta": {}, "title": "ANN"}], "title": "SHFLX global"}]], "groups": [{"title": "WHOI OAFlux"}], "short_name": "lat_lon", "title": "lat_lon"}], "version": "2017-08-23-15-22", "output_viewer_version": "1", "title": "ACME Diagnostics"}